gstly/__init__.cpython-39-x86_64-linux-gnu.so
gstly/errors.cpython-39-x86_64-linux-gnu.so
gstly/gobject_init.cpython-39-x86_64-linux-gnu.so
gstly/logger.cpython-39-x86_64-linux-gnu.so
gstly/pipeline_factories/__init__.cpython-39-x86_64-linux-gnu.so
gstly/pipeline_factories/base.cpython-39-x86_64-linux-gnu.so
gstly/pipeline_factories/custom.cpython-39-x86_64-linux-gnu.so
gstly/pipeline_factories/http.cpython-39-x86_64-linux-gnu.so
gstly/pipeline_factories/rtsp.cpython-39-x86_64-linux-gnu.so
gstly/stream_reader/__init__.cpython-39-x86_64-linux-gnu.so
gstly/stream_reader/base.cpython-39-x86_64-linux-gnu.so
gstly/stream_reader/gst.cpython-39-x86_64-linux-gnu.so
gstly/stream_reader/runtime_options.cpython-39-x86_64-linux-gnu.so
gstly/utils/gstcallbacks.cpython-39-x86_64-linux-gnu.so
gstly/utils/gstreamer.cpython-39-x86_64-linux-gnu.so
gstly/utils/timing.cpython-39-x86_64-linux-gnu.so
gstly-0.4.15.dist-info/METADATA
gstly-0.4.15.dist-info/WHEEL
gstly-0.4.15.dist-info/RECORD
